README.md
setup.py
base_gui/__init__.py
base_gui/base_window.py
base_gui/config.py
base_gui.egg-info/PKG-INFO
base_gui.egg-info/SOURCES.txt
base_gui.egg-info/dependency_links.txt
base_gui.egg-info/top_level.txt