Metadata-Version: 1.1
Name: base-gui
Version: 0.1.2
Summary: A wrapper for Tkinter to             equip your backend program with GUI easily
Home-page: https://github.com/onestraw/base_gui
Author: onestraw
Author-email: hexiaowei91@gmail.com
License: MIT
Platform: UNKNOWN
Classifier: Intended Audience :: Developers
Classifier: License :: OSI Approved :: MIT License
Classifier: Operating System :: MacOS :: MacOS X
Classifier: Operating System :: Microsoft :: Windows
Classifier: Operating System :: POSIX
Classifier: Programming Language :: Python :: 2
